{
 "align_labels_right": 0, 
 "creation": "2018-12-19 19:19:30.961334", 
 "css": ".print-format {\n\tpadding: 0.25in;\n\tfont-size: 9pt;\n}\n\n.print-format td, .print-format th {\n    vertical-align: middle !important;\n}\n.print-format td {\npadding-top:3px !important;\npadding-bottom:3px !important;\n}\n\ntable tr {\n        page-break-inside: avoid !important;\n}\n.page-break\n{\npage-break-inside: avoid !important;\npage-break-after: avoid !important;\n}\n\n.print-format { padding: 0.10in; }\n\nhr { margin:0px !important; }\n\n.letter-head { display:none !important;  }\n\n.print-heading { padding-bottom:0px !important;  margin-bottom:0px !important; }\n\n.table {\n    margin: 2px 0px !important;\n}", 
 "custom_format": 0, 
 "default_print_language": "en", 
 "disabled": 0, 
 "doc_type": "Stock Reconciliation", 
 "docstatus": 0, 
 "doctype": "Print Format", 
 "font": "Default", 
 "format_data": "[{\"fieldname\": \"print_heading_template\", \"fieldtype\": \"Custom HTML\", \"options\": \"<div class=\\\"print-heading\\\">\\t\\t\\t\\t\\n<h2>Stock Reconciliation<br><small>{{ doc.name }}</small></h2></div>\"}, {\"fieldtype\": \"Section Break\", \"label\": \"\"}, {\"fieldtype\": \"Column Break\"}, {\"print_hide\": 0, \"label\": \"Custom HTML\", \"fieldname\": \"_custom_html\", \"options\": \"<div class=\\\"row data-field\\\">\\n<div class=\\\"col-xs-5\\\"><b>Stock Taken By:</b></div>\\n<div class=\\\"col-xs-7\\\"></div>\\n</div>\", \"fieldtype\": \"HTML\"}, {\"fieldtype\": \"Column Break\"}, {\"print_hide\": 0, \"fieldname\": \"posting_date\", \"align\": \"left\", \"label\": \"Date\"}, {\"print_hide\": 0, \"fieldname\": \"posting_time\", \"align\": \"left\", \"label\": \"Print Time\"}, {\"fieldtype\": \"Section Break\", \"label\": \"\"}, {\"fieldtype\": \"Column Break\"}, {\"print_hide\": 0, \"label\": \"Custom HTML\", \"fieldname\": \"_custom_html\", \"options\": \"<table class=\\\"table table-condensed table-hover table-bordered\\\">\\n  <tbody>\\n        <tr>\\n            <th class=\\\"text-left\\\" style=\\\"width:12%;\\\">Item Code</th>\\n            <th class=\\\"text-left\\\" style=\\\"width:25%;\\\">Item Name</th>\\n            <th class=\\\"text-left\\\" style=\\\"width:12%;\\\">Batch No</th>\\n            <th class=\\\"text-center\\\" style=\\\"width:5%;\\\">System Qty</th>\\n            <th class=\\\"text-center\\\" style=\\\"width:46%;\\\">Physical Qty</th>\\n        </tr>\\n        {%- for row in doc.items -%}\\n        <tr>\\n            <td>{{ row.item_code }}</td>\\n            <td>{{ row.item_name }}</td>\\n            <td>{{ row.batch_no }}</td>\\n            <td class='text-right'>{{ row.get_formatted('current_qty', precision=2) }}</td>\\n            <td></td>\\n        </tr>\\n        {%- endfor -%}\\n    </tbody>\\n</table>\", \"fieldtype\": \"HTML\"}]", 
 "idx": 0, 
 "line_breaks": 0, 
 "modified": "2019-09-27 15:17:29.492752", 
 "modified_by": "Administrator", 
 "module": "Stock", 
 "name": "Daily Stock Count", 
 "owner": "vkb@sundinepro.com", 
 "print_format_builder": 0, 
 "print_format_type": "Server", 
 "show_section_headings": 0, 
 "standard": "Yes"
}